MANIFEST.in
README.rst
setup.py
bin/pyfun-joke-bin-scripts
pyfun/__init__.py
pyfun/command_line.py
pyfun/text.py
pyfun.egg-info/PKG-INFO
pyfun.egg-info/SOURCES.txt
pyfun.egg-info/dependency_links.txt
pyfun.egg-info/entry_points.txt
pyfun.egg-info/not-zip-safe
pyfun.egg-info/requires.txt
pyfun.egg-info/top_level.txt