Metadata-Version: 1.1
Name: pyfun
Version: 0.1.4
Summary: The pyfun joke in the world
Home-page: https://github.com/zhaohangbo/pyfun.git
Author: zhaohangbo
Author-email: zhaohangbo@example.com
License: MIT
Keywords: pyfun joke comedy flying circus
Platform: UNKNOWN
Classifier: Development Status :: 3 - Alpha
Classifier: License :: OSI Approved :: MIT License
Classifier: Programming Language :: Python :: 2.7
Classifier: Topic :: Text Processing :: Linguistic
